solrq/__init__.py
solrq-1.1.2.dist-info/LICENSE
solrq-1.1.2.dist-info/METADATA
solrq-1.1.2.dist-info/WHEEL
solrq-1.1.2.dist-info/top_level.txt
solrq-1.1.2.dist-info/zip-safe
solrq-1.1.2.dist-info/RECORD
